{
  "trans": {
    "home": "home",
    "aboutus": "aboutus",
    "contactus": "contactus",
    "translation": "translation",
    "loading": "loading ...",
    "product": "product",
    "login": "login",
    "lang_en": "english",
    "lang_ar": "العربية",
    "english": "english",
    "arabic": "العربية",
    "russian": "russian",
    "soon": "soon",
    "ar_expo_ru": "Arabic Russian Expition",
    "posts": "posts",
    "users": "users",
    "categories": "categories",
    "search": "search",
    "subscriptions": "subscriptions",
    "news": "news",
    "vendors": "vendors",
    "sponsorships": "sponsorships",
    "gallery": "gallery",
    "subscribers": "subscribers",
    "visitors": "visitors",
    "visitor": "visitor",
    "joinus_and_get_many_features": "joinus and get many features",
    "joinus": "joinus",
    "get_to_know_all_kind_of_subscriptions_and_sponsorships": "get to know all kind of subscriptions and sponsorships",
    "register_as_subscription": "register as subscription",
    "register_as_sponsorship": "register as sponsorship",
    "register_as_visitor": "register as visitor",
    "register_to_receive_latest_expo_news": "register to receive latest expo news",
    "through_this_section_u_can_follow_up_all_news_related_to_this_expo_and_even_more": "through this section you can follow up all news related to this expo and even more",
    "enter_ur_email": "enter ur email",
    "notify_me": "notify me",
    "latest_news": "latest news",
    "through_this_section_get_latest_news_related": "through this section get latest news related",
    "through_this_section_find_out_all_companies_related_to_your_interested_field": "through this section find out all companies related to your interested field",
    "navigate_to_more": "navigate to more",
    "browse_the_companies_participating_in_the_exhibition": "browse the companies participating in the exhibition",
    "find_the_interface": "find the interface",
    "welcome_back": "welcome back",
    "welcome_back_Please_enter_the_following_information": "welcome back! Please enter the following information",
    "email_address": "email address",
    "password": "password",
    "remember_me_for_days": "remember me for 30 days",
    "investment_opportunity": "investment opportunity",
    "subscribe_now": "subscribe now",
    "view_company_details": "view company details",
    "sort": "sort",
    "search_now": "search now",
    "ar": "ar",
    "en": "en",
    "ru": "ru",
    "description": "description",
    "services": "services",
    "terms": "terms",
    "address": "address",
    "previous": "previous",
    "next": "next",
    "all_rights_reserved": "all rights reserved",
    "register_now_to_subscribe": "register now to subscribe",
    "search_all_subscribed_companies": "search all subscribed companies",
    "process_success": "successful process",
    "process_failure": "unsuccessful process",
    "confirm_payment": "confirm payment",
    "total": "total",
    "net_total": "net total",
    "discount": "discount",
    "order_success_message": "order success message",
    "order_success_title": "order success title",
    "order_failure_message": "order failure message",
    "order_failure_title": "order failure title",
    "order_status": "order status",
    "order_id": "order id",
    "subscription": "subscription",
    "sponsorship": "sponsorship",
    "membership_type": "membership_type",
    "beneficiary_name": "beneficiary_name",
    "continue": "continue",
    "choose_language": "language",
    "all_participants": "all participants",
    "welcome": "welcome",
    "confirm_password": "confirm password",
    "agree_to": "agree to",
    "the_terms_and_conditions": "the terms and conditions",
    "already_have_an_account": "already have an account?",
    "Welcome_Register_now_and_join_us": "Welcome ! Register now and join us !",
    "registered_successfully": "registered successfully",
    "forgot_password": "forgot password?",
    "sign_in": "sign in",
    "Dont_have_an_account": "Don't have an account",
    "create_an_account": "Create an account",
    "post_index": "post_index",
    "ur_request_is_pending_processed_plz_wait": "your request is pending processed please wait",
    "name": "name",
    "email": "email",
    "message": "message",
    "phone": "phone",
    "send": "send",
    "required": "required",
    "mandatory": "required",
    "optional": "optional",
    "validation.required": "{{field}} is required",
    "validation.email": "email is not in a correct form.",
    "validation.min": "must enter the min limit",
    "validation.max": "must be less than the max limit",
    "validation.matches": "enter a valid format",
    "validation.group_required_min": "some groups still required {{field}}",
    "validation.group_required_max": "some groups still required {{field}}",
    "validation.password_comfirmation": "should match password",
    "contactus_message": "contactus message",
    "payment_confirmation": "payment confirmation",
    "plz_confirm_membership_selected_and_ur_company_information": "please confirm membership selected and ur company information",
    "membership_selected": "membership selected",
    "go_to_payment_page": "go to payment page",
    "print": "print",
    "not_found": "not found",
    "element_u_looking_for_does_not_exist": "element you looking for does not exist",
    "return_home": "return home",
    "empty_results": "empty results",
    "empty_results_messsage": "empty results messsage",
    "reset": "reset",
    "KSA": "saudi ryial",
    "USA": "american dollars",
    "RU": "russian ruble",
    "contactus_information": "contactus information",
    "subscribers_description": "all companies subscribed in exibition",
    "sponsors_description": "all sponsors subscribed in exibition",
    "website": "website",
    "social_media_links": "social media links",
    "my_account": "my_account",
    "control_account_information": "control account information",
    "back_to_home": "back to home",
    "logout": "logout",
    "main_subscripers": "main subscribers",
    "register_now_and_learn_about_the_partner_and_sponsor_packages": "Register now and learn about the subscribers and sponsor packages",
    "register_as_a_subscriper": "register as a subscriber",
    "register_now_and_learn_about_sponsorship_packages": "register now and learn about sponsorship packages",
    "register_as_a_sponsor": "register as a sponsor",
    "through_this_section_you_can_browse_the_latest_news": "Through this section, you can browse the latest news and articles related to the exhibition and the companies participating in the exhibition",
    "control_my_account": "control my account",
    "u_must_be_registered_as_company_register_now_or_update_ur_account": "you must be registered as company register now or update ur account",
    "name.ar": "name in arabic",
    "name.en": "name in english",
    "name.ru": "name in russian",
    "description.ar": "description in arabic",
    "description.en": "description in english",
    "description.ru": "description in russian",
    "services.ar": "services in arabic",
    "services.en": "services in english",
    "services.ru": "services in russian",
    "aboutus.ar": "aboutus in arabic",
    "aboutus.en": "aboutus in english",
    "aboutus.ru": "aboutus in russian",
    "terms.ar": "terms in arabic",
    "terms.en": "terms in english",
    "terms.ru": "terms in russian",
    "address.ar": "address in arabic",
    "address.en": "address in english",
    "address.ru": "address in russian",
    "policy.ar": "policy in arabic",
    "policy.en": "policy in english",
    "policy.ru": "policy in russian",
    "caption.ar": "caption in arabic",
    "caption.en": "caption in english",
    "caption.ru": "caption in russian",
    "submit": "submit",
    "download_the_exhibition_brochure": "download the exhibition brochure",
    "featured": "featured",
    "profile": "profile",
    "control_information": "control my information",
    "registeration": "registeration",
    "a_key_partner_and_sponsor": "a key partner and sponsor",
    "investment_opportunities": "investment opportunities",
    "participant_in_events": "participant in events",
    "seminar_during_the_exhibition": "seminar during the exhibition",
    "mobile": "mobile",
    "whatsapp": "whatsapp",
    "facebook": "facebook",
    "instagram": "instagram",
    "twitter": "twitter",
    "snap": "snap",
    "tiktok": "tiktok",
    "linked": "linked",
    "iphone": "iphone",
    "android": "android",
    "longitude": "longitude",
    "latitude": "latitude",
    "keywords": "keywords",
    "image": "image",
    "logo": "logo",
    "banner": "banner",
    "username": "username",
    "company": "company",
    "role": "role",
    "country": "country",
    "more_details": "more details",
    "upgrade_your_account": "upgrade your account",
    "back": "back",
    "membership_features": "membership features",
    "get_access_now_there_is_offer": "get access now there is offer",
    "subscribe_now_to_book_ur_place": "subscribe now to book ur place",
    "create_an_account_as_subscription": "create an account as subscription",
    "create_an_account_as_visitor": "create an account as visitor",
    "account_details": "account details",
    "change_account_information": "change account information",
    "modify_password": "modify password",
    "modify_your_password": "modify your password",
    "basic_information": "basic information",
    "change_your_company_information": "change your company information",
    "company_description": "company description",
    "add_information_about_your_company": "add information about your company",
    "company_services": "company services",
    "add_your_company_services": "add your company services",
    "about_us": "about us",
    "add_an_overview_of_your_company": "add an overview of your company",
    "upload_the_pictures": "upload the pictures",
    "upload_photos_of_your_company": "upload photos of your company",
    "company_links": "company links",
    "enter_the_company_links": "enter the company links",
    "subtype": "subtype",
    "choose_the_type_of_subscription_or_sponsorship": "choose the type of subscription or sponsorship",
    "payment_process": "payment process",
    "go_to_the_payment_page": "go to the payment page",
    "View_profile": "View profile",
    "You_can_see_your_profile_from_here": "You can see your profile from here",
    "update_information": "update information",
    "saving_information": "saving information",
    "password_confirmation": "password comfirmation",
    "current_password": "current password",
    "new_password": "new password",
    "new_password_comfirmation": "new password comfirmation",
    "search_all_companies": "search all companies",
    "enter_company_name_or_the_word_u_willing_to_search": "enter company name or the word u willing to search",
    "register_to_participate_in_the_exhibition": "register to participate in the exhibition",
    "company_information": "company information",
    "company_website_link": "company website link",
    "download_logo": "upload logo",
    "exhibition_photos": "exhibition photos",
    "upload_file": "upload file",
    "or_drag_and_drop": "or drag and drop",
    "select_the_region_in_the_gallery": "select the region in the gallery",
    "zone_a_desc": "Zone A represents the golden zone and has 3 different zones with areas of 10 m, 15 m and 20 m and prices start from $1000",
    "zone_b_desc": "Zone B represents the silver zone and has 3 different zones of 10 sqm, 15 sqm and 20 sqm, and prices start at $500",
    "zone_c_desc": "Area C represents the platinum area and has 3 different areas of 10 sqm, 15 sqm and 20 sqm, and prices start at $300",
    "zone_d_desc": "Zone D represents the bronze zone and has 3 different zones of 10 m, 15 m and 20 m and prices start at $150",
    "select_the_region": "select the region",
    "choose_the_size_of_stand_you_want": "choose the size of stand you want",
    "price": "price",
    "companies": "companies",
    "zone": "zone",
    "no_data_found": "no data found",
    "your_deals": "your deals",
    "offers": "offers",
    "landing": "landing",
    "signup": "sign up",
    "dont_have_an_account": "dont have an account",
    "phone_number": "phone number",
    "by_tapping_sign_up": "by tapping sign up. you agree to picks",
    "terms_and_conditions": "terms and conditions",
    "privacy_policy": "privacy policy",
    "plz_enter_the_6_digits_code_that_was_sent_to_number": "please enter the 6 digits code that was sent to number",
    "faqs": "faqs",
    "faqs_full": "frequent answered questions",
    "select_area": "select area",
    "select_country": "select country",
    "landing_title1": "restaurant food, takeaway and groceries. ",
    "delivered": "delivered.",
    "lets_go": "let's go",
    "or": "or",
    "log_in": "log in",
    "for_your_saved_addresses": "for your saved addresses.",
    "discover_the_new": "discover the new",
    "picks": "picks",
    "app": "app",
    "flash_daliy_offers": "flash & daliy offers",
    "no_order_calls": "no order calls",
    "tracking_orders": "tracking orders",
    "flash_offer_desc": "no specific day or specific time! Our offers are available throughout the week on all items and restaurants.",
    "order_calls_desc": "order your favorite food easier, faster, and without phone calls.",
    "tracking_orders_desc": "Want to know your order status? No problem, Now you can know exactly where your order is throughout the delivery process.",
    "partner_with_us": "partner with us",
    "join_us_desc": "Join Picks and reach more customers than ever.We handle delivery, so you can focus on the food",
    "get_started": "get started",
    "everything_you_crave_delivered": "everything you crave, delivered.",
    "about_us_desc": "looking for your breakfast,snaks or any food offers near to you ,we bring all of this closer to you with just a click of a button.",
    "see_all": "see all",
    "featured_stores": "featured stores",
    "️flash_offers": "️flash offers",
    "new_picks": "new picks",
    "️flash_offer": "️flash offer",
    "pickup": "pickup",
    "delivery": "delivery",
    "join_us": "join us",
    "join_us_description": "join us description",
    "verification_code": "verification code",
    "confirm": "confirm",
    "didnot_receive_the_code_yet": "didn't receive the code yet ?",
    "resend": "resend",
    "enter_your_phone_number": "enter your phone number",
    "login_txt": "Whether you're crating an account or signing back in , let's start with your number.",
    "add_ur_resturant": "add your resturant",
    "let_us_talk": "let us talk",
    "first_name": "first name",
    "last_name": "last name",
    "welcome_to_picks": "welcome to picks",
    "enter_your_personal_information_to_continue": "enter your personal information to continue.",
    "enter_account_phone_number": "enter account phone number",
    "enter_the_mobile_number_of_your_account_to_send_a_password_change_OTP_messsage": "enter the mobile number of your account to send a password change OTP messsage",
    "send_otp": "send OTP",
    "forget_password": "forget password",
    "send_otp_success": "otp is sent successfully",
    "user_not_found": "user not found",
    "save": "save",
    "change_password_success": "password changed successfully",
    "rating_and_reviews": "rating and reviews",
    "search_in_menu": "search in menu",
    "full_menu": "full menu",
    "off": "off",
    "ratings": "ratings",
    "hide": "hide",
    "show_more": "show more",
    "why_us": "so, why",
    "choose": "choose",
    "us": "us?",
    "learn_about_the_most_important_features_of_the_Picks_app": "learn about the most important features of the Picks app",
    "add_to_cart": "add to cart",
    "select_up_to": "min order is {{min}} and the max {{max}}",
    "max": "max",
    "min": "min",
    "and": "and",
    "restaurants": "restaurants",
    "cuisines": "cuisines",
    "popular_areas": "popular areas",
    "more_areas": "more areas",
    "copy_right": "picks, Inc. All rights reserved.",
    "order_time": "order time",
    "delivery_fees": "delivery fees",
    "open_now": "open now",
    "closed_now": "closed now",
    "select_branch": "select branch",
    "start_order": "start order",
    "big_deals": "big deals",
    "group": "group",
    "flash_offer": "flash offer",
    "policies": "policies",
    "added_to_cart_successfully": "added to cart successfully",
    "unauthenticated": "please login first or register.",
    "popular_search": "popular search",
    "history_search": "history search",
    "browse_picks": "browse picks",
    "results_not_found": "no results found",
    "results_not_found_message": "we couldn't find any results. check the speling or try searching again.",
    "not_available": "not available",
    "login_or_signup_to_continue": "login or Sign up to continue to your account data",
    "discover_the_new_picks_app": "discover the new Picks",
    "download_now": "download now",
    "favorites": "favorites",
    "account": "account",
    "promotions": "promotions",
    "addresses": "addresses"
  }
}